pipreqs/__init__.py
pipreqs/mapping
pipreqs/pipreqs.py
pipreqs/stdlib
pipreqs_fivetran-1.1.0.dist-info/AUTHORS.rst
pipreqs_fivetran-1.1.0.dist-info/LICENSE
pipreqs_fivetran-1.1.0.dist-info/METADATA
pipreqs_fivetran-1.1.0.dist-info/WHEEL
pipreqs_fivetran-1.1.0.dist-info/entry_points.txt
pipreqs_fivetran-1.1.0.dist-info/RECORD
