Metadata-Version: 2.3
Name: pipreqs-fivetran
Version: 1.1.0
Summary: Pip requirements.txt generator based on imports in project
License: Apache-2.0
Keywords: pip,requirements,imports
Author: Fivetran
Author-email: developers@fivetran.com
Requires-Python: >=3.9, <3.15
Classifier: Development Status :: 4 - Beta
Classifier: Intended Audience :: Developers
Classifier: License :: OSI Approved :: Apache Software License
Classifier: Natural Language :: English
Classifier: Programming Language :: Python :: 3
Classifier: Programming Language :: Python :: 3.9
Classifier: Programming Language :: Python :: 3.10
Classifier: Programming Language :: Python :: 3.11
Classifier: Programming Language :: Python :: 3.12
Classifier: Programming Language :: Python :: 3.13
Classifier: Programming Language :: Python :: 3.14
Provides-Extra: dev
Requires-Dist: coverage (>=7.3.2) ; extra == "dev"
Requires-Dist: docopt (>=0.6.2)
Requires-Dist: flake8 (>=6.1.0) ; extra == "dev"
Requires-Dist: ipython (>=8.12.3)
Requires-Dist: nbconvert (>=7.11.0)
Requires-Dist: sphinx (>=7.2.6) ; (python_version >= "3.9") and (extra == "dev")
Requires-Dist: tox (>=4.11.3) ; extra == "dev"
Requires-Dist: yarg (>=0.1.9)
